README.md
setup.cfg
setup.py
pymongal/__init__.py
pymongal/database.py
pymongal/database_dict.py
pymongal/database_mongo.py
pymongal.egg-info/PKG-INFO
pymongal.egg-info/SOURCES.txt
pymongal.egg-info/dependency_links.txt
pymongal.egg-info/requires.txt
pymongal.egg-info/top_level.txt
tests/__init__.py
tests/common_tests.py
tests/test_dict_database.py
tests/test_mongo_database.py