Metadata-Version: 1.1
Name: pymongal
Version: 0.0.2
Summary: MongoDB Abstraction Library
Home-page: https://github.com/research-software-directory/pymongal
Author: Tom Klaver
Author-email: t.klaver@esciencecenter.nl
License: Apache 2.0
Download-URL: https://github.com/Tommos0/pyzenodo/archive/0.0.2.tar.gz
Keywords: mongodb,abstraction,orm
Platform: UNKNOWN
Classifier: Programming Language :: Python
Classifier: Programming Language :: Python :: 3.4
Classifier: Programming Language :: Python :: 3.5
Classifier: Programming Language :: Python :: 3.6
Classifier: Programming Language :: Python :: 3.7
Classifier: Intended Audience :: Developers
Classifier: Intended Audience :: Education
Classifier: License :: OSI Approved :: Apache Software License
Classifier: Operating System :: OS Independent
Classifier: Topic :: Software Development :: Libraries :: Python Modules
Classifier: Topic :: Scientific/Engineering
